dpart/__init__.py
dpart/dpart.py
dpart/engines/__init__.py
dpart/engines/dp_synthpop.py
dpart/engines/independent.py
dpart/engines/priv_bayes.py
dpart/methods/__init__.py
dpart/methods/decision_tree_classifier.py
dpart/methods/histogram_sampler.py
dpart/methods/linear_regression.py
dpart/methods/logistic_regression.py
dpart/methods/probability_tensor.py
dpart/methods/random_forest_classifier.py
dpart/methods/base/__init__.py
dpart/methods/base/category_sampler.py
dpart/methods/base/classifier_sampler.py
dpart/methods/base/numerical_sampler.py
dpart/methods/base/regressor_sampler.py
dpart/methods/base/sampler.py
dpart/methods/utils/__init__.py
dpart/methods/utils/bin_encoder.py
dpart/methods/utils/decorators.py
dpart/methods/utils/dp_utils.py
dpart/methods/utils/sklearn_encoder.py
dpart/methods/utils/stats.py
dpart/utils/__init__.py
dpart/utils/kahn.py
dpart/utils/dependencies/__init__.py
dpart/utils/dependencies/dependency_manager.py
dpart/utils/dependencies/selection.py
dpart-0.1.2.dist-info/LICENSE
dpart-0.1.2.dist-info/METADATA
dpart-0.1.2.dist-info/WHEEL
dpart-0.1.2.dist-info/top_level.txt
dpart-0.1.2.dist-info/RECORD
