Metadata-Version: 2.1
Name: dpart
Version: 0.1.2
Summary: dpart: General, flexible, and scalable framework for differentially private synthetic data generation
Home-page: https://github.com/hazy/dpart
Author: Sofiane Mahiou, Kai Xu, Georgi Ganev
Author-email: info@hazy.com
Project-URL: Bug Tracker, https://github.com/hazy/dpart/issues
Classifier: Programming Language :: Python :: 3
Classifier: License :: OSI Approved :: MIT License
Classifier: Operating System :: OS Independent
Requires-Python: >=3.7
License-File: LICENSE
Requires-Dist: numpy (==1.22.3)
Requires-Dist: pandas (==1.4.2)
Requires-Dist: scikit-learn (==1.0.2)
Requires-Dist: diffprivlib (==0.5.1)
